fractaldna/__init__.py
fractaldna/__main__.py
fractaldna/dna_models/basepair.py
fractaldna/dna_models/dnachain.py
fractaldna/dna_models/dnapositions.py
fractaldna/dna_models/molecules.py
fractaldna/exceptions.py
fractaldna/py.typed
fractaldna/structure_models/hilbert.py
fractaldna/structure_models/random_placements.py
fractaldna/structure_models/voxelisation.py
fractaldna/utils/__init__.py
fractaldna/utils/constants.py
fractaldna/utils/logging.py
fractaldna/utils/rotations.py
fractaldna/utils/sequence.py
fractaldna-0.7.0.dist-info/METADATA
fractaldna-0.7.0.dist-info/WHEEL
fractaldna-0.7.0.dist-info/entry_points.txt
fractaldna-0.7.0.dist-info/licenses/LICENSE
fractaldna-0.7.0.dist-info/RECORD
