Metadata-Version: 2.4
Name: fractaldna
Version: 0.7.0
Summary: FractalDNA is a Python package built to generate DNA geometries for simulations
License: MIT
License-File: LICENSE
Keywords: dna,geant4,simulation,modelling
Author: Nathanael Lampe
Requires-Python: >=3.11,<4.0.0
Classifier: Development Status :: 4 - Beta
Classifier: Intended Audience :: Developers
Classifier: Intended Audience :: Science/Research
Classifier: License :: OSI Approved :: MIT License
Classifier: Operating System :: OS Independent
Classifier: Programming Language :: Python :: 3
Classifier: Programming Language :: Python :: 3.11
Classifier: Programming Language :: Python :: 3.12
Classifier: Programming Language :: Python :: 3.13
Classifier: Programming Language :: Python :: 3.14
Classifier: Programming Language :: Python :: 3.8
Classifier: Programming Language :: Python :: 3.9
Classifier: Topic :: Scientific/Engineering :: Bio-Informatics
Classifier: Topic :: Scientific/Engineering :: Medical Science Apps.
Classifier: Topic :: Software Development :: Libraries :: Python Modules
Provides-Extra: mayavi
Requires-Dist: PyQt5 (>=5.15.9,<6.0.0) ; extra == "mayavi"
Requires-Dist: matplotlib (>3.4.3)
Requires-Dist: mayavi (>=4.8.1,<5.0.0) ; extra == "mayavi"
Requires-Dist: numpy (>1.22.0)
Requires-Dist: pandas (>1.3.3)
Requires-Dist: scipy (>1.8.0)
Requires-Dist: tqdm (>4.62.3)
Requires-Dist: vtk (>=9.2.6,<10.0.0) ; extra == "mayavi"
Project-URL: Documentation, https://natl.github.io/fractaldna
Project-URL: Homepage, https://github.com/natl/fractaldna
Project-URL: Repository, https://github.com/natl/fractaldna
